alexander_fw/__init__.py
alexander_fw/utils.py
alexander_fw/dto/__init__.py
alexander_fw/dto/actor_msg.py
alexander_fw/dto/basic_msg.py
alexander_fw/dto/input_msg.py
alexander_fw/dto/intent_msg.py
alexander_fw/dto/utils.py
alexander_fw/manager/__init__.py
alexander_fw/manager/actor.py
alexander_fw/manager/intent.py
alexander_fw/manager/manager.py
alexander_fw/reactor/__init__.py
alexander_fw/reactor/emitter.py
alexander_fw/reactor/events.py
alexander_fw/reactor/exceptions.py
alexander_fw/reactor/module.py
alexander_fw/reactor/service.py
alexander_fw/service/__init__.py
alexander_fw/service/communicator.py
alexander_fw/service/dispatcher.py
alexander_fw/service/keystore.py
alexander_fw-0.4.6.dist-info/LICENSE
alexander_fw-0.4.6.dist-info/METADATA
alexander_fw-0.4.6.dist-info/WHEEL
alexander_fw-0.4.6.dist-info/top_level.txt
alexander_fw-0.4.6.dist-info/RECORD
