Metadata-Version: 2.1
Name: alexander-fw
Version: 0.4.6
Summary: UNKNOWN
Home-page: https://github.com/the01/python-alexander
Author: the01
Author-email: jungflor@gmail.com
License: MIT License
Platform: UNKNOWN
Classifier: Development Status :: 4 - Beta
Classifier: Intended Audience :: Developers
Classifier: License :: OSI Approved :: MIT License
Classifier: Natural Language :: English
Classifier: Programming Language :: Python :: 2
Classifier: Programming Language :: Python :: 2.7
Requires-Dist: nameko (<3,>=2.9)
Requires-Dist: flotils (<0.6,>=0.5.0)
